{
  "main": [
    {
      "url": "mailto:contact@willzittlau.com",
      "title": "Email Enquiries",
      "img": "email"
    },
    {
      "url": "https://www.instagram.com/willzittlau/",
      "title": "Instagram",
      "img": "instagram"
    },
    {
      "url": "https://tiktok.com/@willzittlau",
      "title": "TikTok",
      "img": "tiktok"
    },
    {
      "url": "https://www.strava.com/athletes/8709142",
      "title": "Strava",
      "img": "strava"
    },
    {
      "url": "https://willzittlau.com/",
      "title": "Personal Blog",
      "img": "blog"
    },
    {
      "url": "https://getaccountable.ca",
      "title": "Mobile app I'm building",
      "img": "accountable"
    },
    {
      "url": "https://skiforecast.herokuapp.com",
      "title": "Ski / Weather Forecast",
      "img": "forecast"
    },
    {
      "url": "https://www.paypal.me/willzittlau",
      "title": "Buy me a coffee",
      "img": "coffee"
    }
  ],
  "icon": [
    {
      "url": "https://tiktok.com/@willzittlau",
      "type": "fab",
      "name": "tiktok"
    },
    {
      "url": "https://www.instagram.com/willzittlau/",
      "type": "fab",
      "name": "instagram"
    },
    {
      "url": "https://www.strava.com/athletes/8709142",
      "type": "fab",
      "name": "strava"
    },
    {
      "url": "https://github.com/willzittlau",
      "type": "fab",
      "name": "github"
    },
    {
      "url": "https://www.linkedin.com/in/will-zittlau/",
      "type": "fab",
      "name": "linkedin"
    },
    {
      "url": "mailto:contact@willzittlau.com",
      "type": "fas",
      "name": "envelope"
    }
  ]
}